logger/__init__.py
logger/logger_handler.py
logger/conf/__init__.py
logger/conf/config.py
logger/util/__init__.py
logger/util/utils.py
logger/writer/__init__.py
logger/writer/log_writer.py
pyclay_logger-0.2.dist-info/LICENSE
pyclay_logger-0.2.dist-info/METADATA
pyclay_logger-0.2.dist-info/WHEEL
pyclay_logger-0.2.dist-info/top_level.txt
pyclay_logger-0.2.dist-info/RECORD
